calling/__init__.py
calling-0.dev0.dist-info/METADATA
calling-0.dev0.dist-info/WHEEL
calling-0.dev0.dist-info/licenses/LICENSE
calling-0.dev0.dist-info/RECORD
