Metadata-Version: 2.3
Name: calling
Version: 0.dev0
Summary: Model python function calls
Author-email: Rob Thatcher <thatcr@gmail.com>
License: MIT License
License-File: LICENSE
Classifier: License :: OSI Approved :: MIT License
Requires-Python: >=3.9
